golpy/.DS_Store
golpy/__init__.py
golpy/__main__.py
golpy/util.py
golpy-0.3.0.dist-info/LICENSE
golpy-0.3.0.dist-info/METADATA
golpy-0.3.0.dist-info/WHEEL
golpy-0.3.0.dist-info/entry_points.txt
golpy-0.3.0.dist-info/RECORD
