Metadata-Version: 2.1
Name: golpy
Version: 0.3.0
Summary: Efficient Conway's Game of Life using NumPy
Home-page: https://github.com/zeta611/py-game-of-life
License: MIT
Keywords: Game of Life
Author: Jay Lee
Author-email: jaeho.lee@snu.ac.kr
Requires-Python: >=3.9,<4.0
Classifier: License :: OSI Approved :: MIT License
Classifier: Programming Language :: Python :: 3
Classifier: Programming Language :: Python :: 3.9
Classifier: Programming Language :: Python :: 3.10
Classifier: Programming Language :: Python :: 3.11
Classifier: Programming Language :: Python :: 3.12
Requires-Dist: Pillow (>=10.3.0,<11.0.0)
Requires-Dist: numpy (>=1.26.4,<2.0.0)
Project-URL: Repository, https://github.com/zeta611/py-game-of-life
